<?xml version="1.0" encoding="UTF-8"?>
<kit>
	<info>
		<name>Spawn</name>
		<donator>false</donator>
	</info>

	<item id="1">
		<slot>boots</slot>
		<id>301</id>
		<amount>1</amount>
		<name>Leather Boots</name>
		<enchant></enchant>
		<soulbound>true</soulbound>
		<damage></damage>
	</item>

	<item id="3">
		<slot>chestplate</slot>
		<id>299</id>
		<amount>1</amount>
		<name>Leather Chestplate</name>
		<enchant></enchant>
		<soulbound>true</soulbound>
		<damage></damage>
	</item>

	<item id="4">
		<slot>helmet</slot>
		<id>298</id>
		<amount>1</amount>
		<name>Leather Helmet</name>
		<enchant></enchant>
		<soulbound>true</soulbound>
		<damage></damage>
	</item>

	<item id="5">
		<slot>pants</slot>
		<id>300</id>
		<amount>1</amount>
		<name>Leather Pants</name>
		<enchant></enchant>
		<soulbound>true</soulbound>
		<damage></damage>

	<item id="6">
		<slot>0</slot>
		<id>267</id>
		<amount>1</amount>
		<name>Iron Sword</name>
		<enchant></enchant>
		<soulbound>true</soulbound>
		<damage></damage>
	</item>

	<item id="7">
		<slot>1</slot>
		<id>261</id>
		<amount>1</amount>
		<name>Bow</name>
		<enchant>51:1</enchant>
		<soulbound>true</soulbound>
		<damage></damage>
	</item>

	<item id="8">
		<slot>4</slot>
		<id>269</id>
		<amount>1</amount>
		<name>Wooden Shovel</name>
		<enchant></enchant>
		<soulbound>true</soulbound>
		<damage></damage>

	</item>
	<item id="9">
		<slot>2</slot>
		<id>278</id>
		<amount>1</amount>
		<name>Diamond Pickaxe</name>
		<enchant></enchant>
		<soulbound>true</soulbound>
		<damage></damage>
	</item>

	<item id="10">
		<slot>5</slot>
		<id>80</id>
		<amount>64</amount>
		<name>Snow Block</name>
		<enchant></enchant>
		<soulbound>false</soulbound>
		<damage></damage>
	</item>

	<item id="11">
		<slot>6</slot>
		<id>332</id>
		<amount>16</amount>
		<name>Snowball</name>
		<enchant></enchant>
		<soulbound>false</soulbound>
		<damage></damage>
	</item>

	<item id="12">
		<slot>3</slot>
		<id>371</id>
		<amount>8</amount>
		<name>Golden Nugget</name>
		<enchant></enchant>
		<soulbound>false</soulbound>
		<damage></damage>
	</item>

	<item id="13">
		<slot>7</slot>
		<id>260</id>
		<amount>64</amount>
		<name>Apple</name>
		<enchant></enchant>
		<soulbound>false</soulbound>
		<damage></damage>
	</item>

	<item id="14">
		<slot>28</slot>
		<id>262</id>
		<amount>64</amount>
		<name>Arrow</name>
		<enchant></enchant>
		<soulbound>false</soulbound>
		<damage></damage>
	</item>
</kit>